biatoolkit/__init__.py
biatoolkit/basic_client.py
biatoolkit/sankhya_call.py
biatoolkit/settings.py
biatoolkit/test_sankhya.py
biatoolkit/util.py
biatoolkit/schema/__init__.py
biatoolkit/schema/header.py
biatoolkit/validation/__init__.py
biatoolkit/validation/coercion.py
biatoolkit/validation/validation.py
biatoolkit-1.2.3.dist-info/METADATA
biatoolkit-1.2.3.dist-info/WHEEL
biatoolkit-1.2.3.dist-info/top_level.txt
biatoolkit-1.2.3.dist-info/RECORD
