Metadata-Version: 2.4
Name: biatoolkit
Version: 1.2.3
Summary: Biblioteca para desenvolvedores que utilizam o BiaAgentBuilder
Author: Bia Platform Team
Author-email: data.platform@sankhya.com.br
Classifier: Programming Language :: Python :: 3
Classifier: License :: OSI Approved :: MIT License
Classifier: Operating System :: OS Independent
Requires-Python: >=3.10
Dynamic: author
Dynamic: author-email
Dynamic: classifier
Dynamic: description
Dynamic: description-content-type
Dynamic: requires-python
Dynamic: summary
